{
  "name": "Wickedness begins to grow",
  "description": "At the commencement of the sixty-seventh year, the people began to grow exceedingly wicked due to their wealth and desire for gain, leading them to secret murders and plundering.",
  "sources": [
    "Helaman 6:16-17"
  ],
  "date": {
    "year": 67,
    "month": null,
    "day": null,
    "calendar_system": "reign-of-the-judges",
    "miscellaneous": null
  },
  "end_date": null,
  "location": null,
  "participants": null,
  "relative_events": null
}