{
  "name": "Execution of Justice on the Robbers",
  "description": "The Nephites captured all the robbers, casting them into prison. The word of God was preached unto them, and those who repented and covenanted to murder no more were set at liberty, while those who continued in wickedness were condemned and punished according to the law.",
  "sources": [
    "3 Nephi 5:4-5"
  ],
  "date": {
    "year": 1,
    "month": null,
    "day": null,
    "calendar_system": "after-christ",
    "miscellaneous": null
  },
  "end_date": null,
  "location": null,
  "participants": [],
  "relative_events": null
}