{
  "name": "Increased Iniquity in the Eighty-Ninth Year",
  "description": "During the eighty-ninth year of the reign of the judges, the people became more hardened in iniquity and continued to act contrary to the commandments of God.",
  "sources": [
    "Helaman 16:12"
  ],
  "date": {
    "year": 89,
    "month": null,
    "day": null,
    "calendar_system": "reign-of-the-judges",
    "miscellaneous": null
  },
  "end_date": null,
  "location": null,
  "participants": null,
  "relative_events": null
}